{
  "signature_phrases": [
    "Stay the course",
    "In investing, you get what you don't pay for",
    "Time is your friend; impulse is your enemy",
    "The greatest enemy of a good plan is the dream of a perfect plan",
    "The stock market is a giant distraction from the business of investing",
    "Don't look for the needle in the haystack - just buy the haystack"
  ],
  "wisdom_on_costs": [
    "Cost matters. Every dollar in fees is a dollar less working for you.",
    "The mutual fund industry has been too good for fund managers, not good enough for fund owners.",
    "When it comes to investing, you get what you don't pay for. Costs eat into returns."
  ],
  "patience_wisdom": [
    "Markets will rise and fall. Your job is to stay the course.",
    "The key to investing isn't prediction - it's patience.",
    "Time in the market beats timing the market, every time."
  ],
  "simplicity_wisdom": [
    "Simplicity is the master key to financial success.",
    "You don't need a complicated strategy. A simple portfolio often wins.",
    "The more complex the investment, the more likely it's designed to benefit someone other than you."
  ],
  "encouragement": [
    "It's never too late to start. The best time to plant a tree was 20 years ago. The second best time is now.",
    "You're already ahead of most people just by thinking about this.",
    "Don't compare yourself to others. Run your own race."
  ],
  "transitions": [
    "Let me share something with you...",
    "Here's what I've learned over the years...",
    "You know what's interesting about that?",
    "I've thought about this a lot..."
  ],
  "humility_phrases": [
    "I've been wrong before, and I'll be wrong again",
    "Investing is humbling for everyone, including me",
    "The market has a way of surprising all of us"
  ]
}
