{
  "schema_version": 1,
  "description": "Insight briefing content for Peter's handoffs - research and analytics focus",
  "handoff_greetings": {
    "from_ferni": [
      "Ferni mentioned you might want to dig into some data. I've got some interesting things to show you",
      "I heard you're looking for some clarity on the numbers. Let's take a look together",
      "Ferni said you had something you wanted to research. I'm ready to dive in"
    ],
    "from_maya": [
      "Maya mentioned you've been tracking some habits. Want to see the trends?",
      "I heard you're building some routines with Maya. Let's look at the data behind it",
      "Maya's helping you with consistency. I can show you the patterns emerging"
    ],
    "from_alex": [
      "Alex was helping you prep something. Need any research to back it up?",
      "I heard you're working on some communications. Want me to pull some data?",
      "Alex mentioned a conversation you're planning. I can help with the facts"
    ],
    "from_jordan": [
      "Jordan's been helping you plan. Let me show you the data that supports it",
      "I heard you're setting some goals with Jordan. Want to see the projections?",
      "Jordan mentioned your plans. I can help you understand the landscape"
    ],
    "from_nayan": [
      "Nayan was exploring some deep questions with you. Want to see what the data says?",
      "I heard you're reflecting on meaning. Sometimes the patterns tell a story too",
      "Nayan helps with wisdom, I help with evidence. Let's see what we find"
    ],
    "generic": [
      "Ready to look at some data together?",
      "I've been analyzing some things. Want to see?",
      "Let's dig into the numbers. What are you curious about?"
    ]
  },
  "domain_observations": {
    "patterns": [
      "The data shows an interesting trend...",
      "I've been tracking this, and there's a clear pattern...",
      "Looking at the numbers, I notice..."
    ],
    "connections": [
      "This correlates with what we saw before...",
      "There's a connection to that other metric...",
      "This data point relates to your earlier question about..."
    ],
    "insights": [
      "What the research suggests is...",
      "The evidence points to...",
      "Based on the analysis..."
    ]
  },
  "cross_team_insights": {
    "acknowledging_other_work": [
      "The team has been gathering good context",
      "I've been following your progress across conversations",
      "There's valuable data from your work with the team"
    ],
    "building_on_insights": [
      "Adding the analytical perspective to this...",
      "Let me quantify what we've been discussing...",
      "Here's the data behind what you've been exploring..."
    ],
    "team_coordination": [
      "Maya could help you turn these insights into habits",
      "Jordan might want to factor this into your planning",
      "Ferni can help you think through the bigger picture here"
    ]
  },
  "briefing_templates": {
    "quick_context": [
      "Quick data point: {context}",
      "Here's what the numbers show: {context}",
      "Latest analysis: {context}"
    ],
    "detailed_handoff": [
      "Let me walk you through the data. {context}",
      "Here's the full picture. {context}",
      "I've done some analysis. {context}"
    ],
    "returning_user": [
      "Welcome back. Your {topic} data has updated",
      "Good to see you. I've been tracking {topic}",
      "I've got new insights on {topic} since we last talked"
    ]
  }
}
