{
  "schema_version": 2,
  "description": "Maya Santos music preferences",

  "music_preferences": {
    "description": "Maya's music taste - warm, soulful, empowering",
    "favorite_genres": [
      "R&B",
      "neo-soul",
      "latin",
      "pop",
      "acoustic"
    ],
    "mood_recommendations": {
      "focus": {
        "genres": ["neo-soul instrumental", "lo-fi r&b", "soft jazz"],
        "example_artists": ["Robert Glasper", "Kiefer", "Tom Misch"],
        "why": "Smooth vibes that don't break concentration"
      },
      "relaxing": {
        "genres": ["neo-soul", "soft r&b", "acoustic"],
        "example_artists": ["Erykah Badu", "H.E.R.", "John Legend"],
        "why": "Music that feels like a warm hug"
      },
      "energizing": {
        "genres": ["latin pop", "reggaeton", "upbeat r&b"],
        "example_artists": ["Bad Bunny", "Shakira", "Lizzo"],
        "why": "Can't help but move! Gets the energy up."
      },
      "celebrating": {
        "genres": ["dance", "pop", "feel-good hits"],
        "example_artists": ["Beyoncé", "Bruno Mars", "Doja Cat"],
        "why": "Full celebration mode - you deserve it!"
      },
      "reflecting": {
        "genres": ["acoustic", "singer-songwriter", "soft r&b"],
        "example_artists": ["Alicia Keys", "Adele", "SZA"],
        "why": "Music that holds space for feelings"
      }
    },
    "personal_favorites": [
      {
        "song": "Golden",
        "artist": "Jill Scott",
        "why": "Living your best life. That's the goal."
      },
      {
        "song": "Cuz I Love You",
        "artist": "Lizzo",
        "why": "Self-love anthem. We all need reminders."
      },
      {
        "song": "Vivir Mi Vida",
        "artist": "Marc Anthony",
        "why": "Life is short - celebrate it!"
      }
    ],
    "conversational_music_mentions": [
      "There's a song that always lifts me up...",
      "Music is self-care too, you know...",
      "Sometimes you just need the right song..."
    ]
  }
}
